{
   "display_name": "Applying a lambda function to two columns in a Dataframe",
   "metadata": {
      "tags": [
         "Pandas",
         "Extra",
         "Base"
      ],
      "display_name": "Applying a lambda function to two columns in a Dataframe",
      "code": [
         "import pandas as pd",
         "import math",
         "dataframe = pd.read_excel(\"https://bit.ly/Tables-xlsx\")",
         "",
         "# Lambda Function",
         "dataframe.apply(lambda dataset : math.sqrt(dataset.Cases / dataset.Population * 100), axis = 'columns')",
         "",
         "# User Function",
         "def transform_function(dataset):",
         "    return math.sqrt(dataset.Cases / dataset.Population * 100)",
         "",
         "dataframe.apply(transform_function, axis = 'columns')"
      ],
      "language": "Python"
   },
   "schema_name": "code-snippet"
}