{
   "display_name": "Getting the last rows of a Dataframe",
   "metadata": {
      "tags": [
         "Pandas",
         "Data Analysis",
         "Exploring Data"
      ],
      "display_name": "Getting the last rows of a Dataframe",
      "code": [
         "import pandas as pd",
         "dataframe = pd.read_excel(\"https://bit.ly/Tables-xlsx\")",
         "",
         "# Use an argument if you want to specify a concrete number of lines",
         "dataframe.tail(2)"
      ],
      "language": "Python"
   },
   "schema_name": "code-snippet"
}