{
   "display_name": "Special Case - Swapping Rows and Columns",
   "metadata": {
      "tags": [
         "Pandas",
         "Data Cleaning"
      ],
      "display_name": "Special Case - Swapping Rows and Columns",
      "code": [
         "import pandas as pd",
         "import numpy as np",
         "",
         "text_file = open(\"data.csv\", \"w\")",
         "text_file.write(",
         "\"\"\"",
         "Attrib,Ryan,Arjun,john,Rosy",
         "Class,IV,III,III,V",
         "English,90,85,90,95",
         "Math,95,90,85,80",
         "Science,95,90,90,90",
         "Computer,98,95,90,85",
         "Year,2020,2020,2020,2020",
         "\"\"\")",
         "text_file.close()",
         "",
         "dataframe = pd.read_csv(\"data.csv\")",
         "",
         "display(dataframe)",
         "",
         "(dataframe",
         "    .set_index(\"Attrib\").rename_axis(None)",
         "    .transpose()",
         "    .reset_index()",
         "    .rename( columns = { 'index' : 'Student' })",
         " )"
      ],
      "language": "Python"
   },
   "schema_name": "code-snippet"
}